[
    {
        "subject": "Math",
        "priority": "high"
    },
    {
        "subject": "Math",
        "priority": "medium"
    },
    {
        "subject": "Math",
        "priority": "low"
    },
    {
        "subject": "Science",
        "priority": "high"
    },
    {
        "subject": "Science",
        "priority": "medium"
    },
    {
        "subject": "Science",
        "priority": "low"
    },
    {
        "subject": "History",
        "priority": "low"
    },
    {
        "subject": "English",
        "priority": "high"
    },
    {
        "subject": "English",
        "priority": "medium"
    },
    {
        "subject": "English",
        "priority": "low"
    },
    {
        "subject": "Art",
        "priority": "high"
    },
    {
        "subject": "History",
        "priority": "medium"
    },
    {
        "subject": "Art",
        "priority": "low"
    },
    {
        "subject": "Music",
        "priority": "high"
    }
]